smarta2a/__init__.py
smarta2a/agent/a2a_agent.py
smarta2a/agent/a2a_human.py
smarta2a/agent/a2a_mcp_server.py
smarta2a/archive/smart_mcp_client.py
smarta2a/archive/subscription_service.py
smarta2a/archive/task_service.py
smarta2a/client/__init__.py
smarta2a/client/a2a_client.py
smarta2a/client/mcp_client.py
smarta2a/client/nats_client.py
smarta2a/file_stores/base_file_store.py
smarta2a/file_stores/local_file_store.py
smarta2a/history_update_strategies/__init__.py
smarta2a/history_update_strategies/append_strategy.py
smarta2a/history_update_strategies/history_update_strategy.py
smarta2a/history_update_strategies/rolling_window_strategy.py
smarta2a/model_providers/__init__.py
smarta2a/model_providers/base_llm_provider.py
smarta2a/model_providers/openai_provider.py
smarta2a/server/__init__.py
smarta2a/server/handler_registry.py
smarta2a/server/json_rpc_request_processor.py
smarta2a/server/request_handler.py
smarta2a/server/server.py
smarta2a/server/state_manager.py
smarta2a/server/webhook_request_processor.py
smarta2a/state_stores/__init__.py
smarta2a/state_stores/base_state_store.py
smarta2a/state_stores/inmemory_state_store.py
smarta2a/utils/__init__.py
smarta2a/utils/agent_discovery_manager.py
smarta2a/utils/prompt_helpers.py
smarta2a/utils/task_builder.py
smarta2a/utils/task_request_builder.py
smarta2a/utils/tools_manager.py
smarta2a/utils/types.py
smarta2a-0.4.30.dist-info/METADATA
smarta2a-0.4.30.dist-info/WHEEL
smarta2a-0.4.30.dist-info/licenses/LICENSE
smarta2a-0.4.30.dist-info/RECORD
