Metadata-Version: 2.4
Name: smarta2a
Version: 0.4.30
Summary: a Python framework that helps you build servers and AI agents that communicate using the A2A protocol
Project-URL: Homepage, https://github.com/siddharthsma/smarta2a
Project-URL: Bug Tracker, https://github.com/siddharthsma/smarta2a/issues
Author-email: Siddharth Ambegaonkar <siddharthsma@gmail.com>
License-File: LICENSE
Classifier: License :: OSI Approved :: MIT License
Classifier: Operating System :: OS Independent
Classifier: Programming Language :: Python :: 3
Requires-Python: >=3.8
Requires-Dist: aiofiles==24.1.0
Requires-Dist: anyio>=4.9.0
Requires-Dist: fastapi>=0.115.12
Requires-Dist: httpx>=0.28.1
Requires-Dist: mcp>=0.1.0
Requires-Dist: nats-py==2.10.0
Requires-Dist: openai>=1.0.0
Requires-Dist: pydantic>=2.11.3
Requires-Dist: sse-starlette>=2.2.1
Requires-Dist: starlette>=0.46.2
Requires-Dist: typing-extensions>=4.13.2
Requires-Dist: uvicorn>=0.34.1
